gwtool/__init__.py
gwtool-0.0.0.dist-info/LICENCE
gwtool-0.0.0.dist-info/METADATA
gwtool-0.0.0.dist-info/WHEEL
gwtool-0.0.0.dist-info/top_level.txt
gwtool-0.0.0.dist-info/RECORD
